getversion/__init__.py
getversion/_version.py
getversion/main.py
getversion/plugin_builtins.py
getversion/plugin_eggs_and_wheels.py
getversion/plugin_importlib_metadata.py
getversion/plugin_setuptools_scm.py
getversion/py.typed
getversion-1.0.2.dist-info/LICENSE
getversion-1.0.2.dist-info/METADATA
getversion-1.0.2.dist-info/WHEEL
getversion-1.0.2.dist-info/top_level.txt
getversion-1.0.2.dist-info/RECORD
