Metadata-Version: 2.1
Name: getversion
Version: 1.0.2
Summary: Get the version number of any python module or package, reliably.
Home-page: https://github.com/smarie/python-getversion
Maintainer: Sylvain MARIE
Maintainer-email: sylvain.marie@se.com
License: BSD 3-Clause
Download-URL: https://github.com/smarie/python-getversion/tarball/1.0.2
Keywords: module version source binary package library PEP345 PEP396 PEP427 pkg_resources setuptools wheel egg egg-info scm git svn
Platform: UNKNOWN
Classifier: Development Status :: 5 - Production/Stable
Classifier: Intended Audience :: Developers
Classifier: Topic :: Software Development :: Libraries :: Python Modules
Classifier: License :: OSI Approved :: BSD License
Classifier: Programming Language :: Python :: 2.7
Classifier: Programming Language :: Python :: 3.5
Classifier: Programming Language :: Python :: 3.6
Classifier: Programming Language :: Python :: 3.7
Classifier: Programming Language :: Python :: 3.8
Requires-Dist: stdlib-list
Requires-Dist: setuptools-scm
Requires-Dist: functools32 ; python_version < "3.2"
Requires-Dist: scandir ; python_version < "3.2"
Requires-Dist: pathlib2 ; python_version < "3.2"
